nndesigndemos/Window.py
nndesigndemos/__init__.py
nndesigndemos/get_package_path.py
nndesigndemos/nndesign.py
nndesigndemos/nndesign_layout.py
nndesigndemos/nndesign_settings.py
nndesigndemos/Chapters/2/Logo_Ch_2.eps
nndesigndemos/Chapters/2/Logo_Ch_2.svg
nndesigndemos/Chapters/2/SingleInputNeuron.png
nndesigndemos/Chapters/2/SingleInputNeuron.svg
nndesigndemos/Chapters/2/nn2d1.png
nndesigndemos/Chapters/2/nn2d1.svg
nndesigndemos/Chapters/2/Old/Logo_Ch_3.eps
nndesigndemos/Chapters/2/Old/SingleInputNeuron.eps
nndesigndemos/Chapters/2/Old/drawing.svg
nndesigndemos/Chapters/2/Old/info_2.svg
nndesigndemos/Chapters/2/Old/nn2d1.pdf
nndesigndemos/Chapters/2/Old/nn2d1.png
nndesigndemos/Chapters/2/Old/nn2d1_1.eps
nndesigndemos/Chapters/2/Old/nn2d1_1.pdf
nndesigndemos/Chapters/2/Old/nn2d1_1.png
nndesigndemos/Chapters/2/Old/nn2d1_1.ps
nndesigndemos/Chapters/2/Old/nn2d1_1.svg
nndesigndemos/Chapters/2/Old/nn2d1_old.svg
nndesigndemos/Chapters/2/Old/nn2d1p.svg
nndesigndemos/Chapters/2_D/2f.svg
nndesigndemos/Chapters/2_D/2f_1.svg
nndesigndemos/Chapters/2_D/2f_1_1.svg
nndesigndemos/Chapters/2_D/3f.svg
nndesigndemos/Chapters/2_D/3f_1.svg
nndesigndemos/Chapters/2_D/4f.svg
nndesigndemos/Chapters/2_D/4f_1.svg
nndesigndemos/Chapters/2_D/Logo_Ch_2.svg
nndesigndemos/Chapters/2_D/Poslin_Decsion_Region.svg
nndesigndemos/Chapters/2_D/poslinNet.svg
nndesigndemos/Chapters/2_D/poslinNet2D.eps
nndesigndemos/Chapters/2_D/poslinNet2D.pdf
nndesigndemos/Chapters/2_D/poslinNet2D.png
nndesigndemos/Chapters/2_D/poslinNet2D.svg
nndesigndemos/Chapters/2_D/poslinNet2D.tiff
nndesigndemos/Chapters/2_D/poslinNet2D_1.svg
nndesigndemos/Chapters/2_D/poslinNet2D_2.svg
nndesigndemos/Chapters/2_D/poslinNet2D_DrHagan.svg
nndesigndemos/Chapters/2_D/poslinNet2Dtemp.svg
nndesigndemos/Chapters/2_D/poslinNet_new.svg
nndesigndemos/Chapters/2_D/Last demo/mdeltalog.m
nndesigndemos/Chapters/2_D/Last demo/radialFunctionExample.m
nndesigndemos/Chapters/2_D/Last demo/test_train_marq3D.m
nndesigndemos-1.1.6.dist-info/METADATA
nndesigndemos-1.1.6.dist-info/WHEEL
nndesigndemos-1.1.6.dist-info/top_level.txt
nndesigndemos-1.1.6.dist-info/RECORD
